solrcmf/__init__.py
solrcmf/admm.py
solrcmf/base.py
solrcmf/blocks.py
solrcmf/constraints.py
solrcmf/crossval.py
solrcmf/initializer.py
solrcmf/initstrategies.py
solrcmf/lrimpute.py
solrcmf/metrics.py
solrcmf/preprocess.py
solrcmf/simulate.py
solrcmf/solrcmf.py
solrcmf/splits.py
solrcmf-0.1.1.dist-info/METADATA
solrcmf-0.1.1.dist-info/WHEEL
solrcmf-0.1.1.dist-info/licenses/LICENSE
solrcmf-0.1.1.dist-info/RECORD
