Metadata-Version: 2.3
Name: solrcmf
Version: 0.1.1
Summary: Tools for integrative analysis in flexible matrix layouts using penalized optimization techniques
Project-URL: Homepage, https://github.com/cyianor/solrcmf
Project-URL: Issues, https://github.com/cyianor/solrcmf/issues
Author-email: Felix Held <felix.held@gmail.com>
License: MIT
Classifier: License :: OSI Approved :: MIT License
Classifier: Operating System :: OS Independent
Classifier: Programming Language :: Python :: 3
Requires-Python: >=3.10
